[
  {
    "uid": 4229490589,
    "password": "JAMIUAR_CODX-ZB54OXJC1",
    "account_id": 1,
    "name": "JAMUL_KGIP6Q",
    "region": "BD"
  },
  {
    "uid": 4229491439,
    "password": "JAMIUAR_CODX-5DSMBIBLA",
    "account_id": 1,
    "name": "JAMUL_PEN3RF",
    "region": "BD"
  },
  {
    "uid": 4229491894,
    "password": "JAMIUAR_CODX-HHA24YYPK",
    "account_id": 1,
    "name": "JAMUL_MHTYBR",
    "region": "BD"
  },
  {
    "uid": 4229492013,
    "password": "JAMIUAR_CODX-PZTHOER2T",
    "account_id": 1,
    "name": "JAMUL_5R0FMW",
    "region": "BD"
  },
  {
    "uid": 4229492716,
    "password": "JAMIUAR_CODX-QTLHITGSB",
    "account_id": 1,
    "name": "JAMUL_QMRLBJ",
    "region": "BD"
  },
  {
    "uid": 4229493563,
    "password": "JAMIUAR_CODX-V0SJP7OIR",
    "account_id": 1,
    "name": "JAMUL_PG8JZC",
    "region": "BD"
  },
  {
    "uid": 4229494705,
    "password": "JAMIUAR_CODX-G5HCQYVDH",
    "account_id": 1,
    "name": "JAMUL_MRD7V2",
    "region": "BD"
  },
  {
    "uid": 4229494850,
    "password": "JAMIUAR_CODX-HXUNYS416",
    "account_id": 1,
    "name": "JAMUL_VH0CZI",
    "region": "BD"
  },
  {
    "uid": 4229495203,
    "password": "JAMIUAR_CODX-JNQG5ZTWD",
    "account_id": 1,
    "name": "JAMUL_GDKW0C",
    "region": "BD"
  },
  {
    "uid": 4229495462,
    "password": "JAMIUAR_CODX-5H0HOVEHE",
    "account_id": 1,
    "name": "JAMUL_PEY1RJ",
    "region": "BD"
  },
  {
    "uid": 4229495649,
    "password": "JAMIUAR_CODX-E9P25C9F4",
    "account_id": 1,
    "name": "JAMUL_SMEDCJ",
    "region": "BD"
  },
  {
    "uid": 4229495816,
    "password": "JAMIUAR_CODX-ETUQVUOIZ",
    "account_id": 1,
    "name": "JAMUL_QZ26DO",
    "region": "BD"
  },
  {
    "uid": 4229496153,
    "password": "JAMIUAR_CODX-D3TAI2LD7",
    "account_id": 1,
    "name": "JAMUL_JB4DSG",
    "region": "BD"
  },
  {
    "uid": 4229496791,
    "password": "JAMIUAR_CODX-PUNTOTXXO",
    "account_id": 1,
    "name": "JAMUL_V0SPA6",
    "region": "BD"
  },
  {
    "uid": 4229501099,
    "password": "JAMIUAR_CODX-OIKGJQER5",
    "account_id": 1,
    "name": "JAMUL_F3R2LP",
    "region": "BD"
  },
  {
    "uid": 4229501262,
    "password": "JAMIUAR_CODX-HPHAAL4O4",
    "account_id": 1,
    "name": "JAMUL_H31W6L",
    "region": "BD"
  },
  {
    "uid": 4229501373,
    "password": "JAMIUAR_CODX-62M2O3LUA",
    "account_id": 1,
    "name": "JAMUL_SEI7RB",
    "region": "BD"
  },
  {
    "uid": 4229501520,
    "password": "JAMIUAR_CODX-YGSZEYJPF",
    "account_id": 1,
    "name": "JAMUL_H1P4RH",
    "region": "BD"
  },
  {
    "uid": 4229501675,
    "password": "JAMIUAR_CODX-XUIYCFSSH",
    "account_id": 1,
    "name": "JAMUL_BWXCCE",
    "region": "BD"
  },
  {
    "uid": 4229501851,
    "password": "JAMIUAR_CODX-1UNNEG1JL",
    "account_id": 1,
    "name": "JAMUL_ZVRXWD",
    "region": "BD"
  },
  {
    "uid": 4229502014,
    "password": "JAMIUAR_CODX-5LVQLOJ4Z",
    "account_id": 1,
    "name": "JAMUL_GKUYFN",
    "region": "BD"
  },
  {
    "uid": 4229502347,
    "password": "JAMIUAR_CODX-EI6QKLN6W",
    "account_id": 1,
    "name": "JAMUL_LJECIV",
    "region": "BD"
  },
  {
    "uid": 4229502617,
    "password": "JAMIUAR_CODX-6XEOPSFGG",
    "account_id": 1,
    "name": "JAMUL_EO22SX",
    "region": "BD"
  },
  {
    "uid": 4229502823,
    "password": "JAMIUAR_CODX-BCKMKUVSA",
    "account_id": 1,
    "name": "JAMUL_VKZHPG",
    "region": "BD"
  },
  {
    "uid": 4229503036,
    "password": "JAMIUAR_CODX-MCELMSBJX",
    "account_id": 1,
    "name": "JAMUL_BWXOIC",
    "region": "BD"
  },
  {
    "uid": 4229503160,
    "password": "JAMIUAR_CODX-9RV90NGBM",
    "account_id": 1,
    "name": "JAMUL_3QIVCE",
    "region": "BD"
  },
  {
    "uid": 4229503400,
    "password": "JAMIUAR_CODX-EZMNHVJX8",
    "account_id": 1,
    "name": "JAMUL_6ZQBJR",
    "region": "BD"
  },
  {
    "uid": 4229503505,
    "password": "JAMIUAR_CODX-8QAOMZUEY",
    "account_id": 1,
    "name": "JAMUL_HY8FDC",
    "region": "BD"
  },
  {
    "uid": 4229503596,
    "password": "JAMIUAR_CODX-GRBKQMPZQ",
    "account_id": 1,
    "name": "JAMUL_Q0XCM6",
    "region": "BD"
  },
  {
    "uid": 4229503687,
    "password": "JAMIUAR_CODX-HT7H4BEZD",
    "account_id": 1,
    "name": "JAMUL_SOHC7G",
    "region": "BD"
  },
  {
    "uid": 4229503786,
    "password": "JAMIUAR_CODX-LHZSMSZRR",
    "account_id": 1,
    "name": "JAMUL_CDRB7H",
    "region": "BD"
  },
  {
    "uid": 4229504219,
    "password": "JAMIUAR_CODX-96IKZJTS8",
    "account_id": 1,
    "name": "JAMUL_4GE8IU",
    "region": "BD"
  },
  {
    "uid": 4229504518,
    "password": "JAMIUAR_CODX-BIJUOA2EL",
    "account_id": 1,
    "name": "JAMUL_ADL78I",
    "region": "BD"
  },
  {
    "uid": 4229504631,
    "password": "JAMIUAR_CODX-VG93UMEZI",
    "account_id": 1,
    "name": "JAMUL_FQ7ED5",
    "region": "BD"
  },
  {
    "uid": 4229504760,
    "password": "JAMIUAR_CODX-30AIZEVUP",
    "account_id": 1,
    "name": "JAMUL_EQKS5A",
    "region": "BD"
  },
  {
    "uid": 4229504902,
    "password": "JAMIUAR_CODX-YK53AZZJ7",
    "account_id": 1,
    "name": "JAMUL_P8PUBW",
    "region": "BD"
  },
  {
    "uid": 4229505034,
    "password": "JAMIUAR_CODX-PGIYWAV58",
    "account_id": 1,
    "name": "JAMUL_SMPGPA",
    "region": "BD"
  },
  {
    "uid": 4229505163,
    "password": "JAMIUAR_CODX-WVT9NYRYA",
    "account_id": 1,
    "name": "JAMUL_F4PMY8",
    "region": "BD"
  },
  {
    "uid": 4229505282,
    "password": "JAMIUAR_CODX-7BAJ0ZRPP",
    "account_id": 1,
    "name": "JAMUL_TVVDC7",
    "region": "BD"
  },
  {
    "uid": 4229505470,
    "password": "JAMIUAR_CODX-IYKATXMQF",
    "account_id": 1,
    "name": "JAMUL_7AHNGI",
    "region": "BD"
  },
  {
    "uid": 4229505567,
    "password": "JAMIUAR_CODX-R7TCAXPV9",
    "account_id": 1,
    "name": "JAMUL_6T5PUT",
    "region": "BD"
  },
  {
    "uid": 4229505726,
    "password": "JAMIUAR_CODX-H6RXBJWHQ",
    "account_id": 1,
    "name": "JAMUL_DO63UK",
    "region": "BD"
  },
  {
    "uid": 4229554534,
    "password": "JAMIUAR_CODX-XVC8YGFKF",
    "account_id": 1,
    "name": "JAMUL_ITS4TD",
    "region": "BD"
  },
  {
    "uid": 4229555162,
    "password": "JAMIUAR_CODX-ECS5CO3FG",
    "account_id": 1,
    "name": "JAMUL_AAK7DN",
    "region": "BD"
  },
  {
    "uid": 4229560519,
    "password": "JAMIUAR_CODX-GVDIQM2PU",
    "account_id": 1,
    "name": "JAMUL_H3XSYD",
    "region": "BD"
  },
  {
    "uid": 4229560634,
    "password": "JAMIUAR_CODX-BE1JC2FGW",
    "account_id": 1,
    "name": "JAMUL_D8BYGZ",
    "region": "BD"
  },
  {
    "uid": 4229560804,
    "password": "JAMIUAR_CODX-TZORVVFPQ",
    "account_id": 1,
    "name": "JAMUL_WG6CFH",
    "region": "BD"
  },
  {
    "uid": 4229561692,
    "password": "JAMIUAR_CODX-VNVZFRPSG",
    "account_id": 1,
    "name": "JAMUL_LANTWX",
    "region": "BD"
  },
  {
    "uid": 4229562009,
    "password": "JAMIUAR_CODX-6ZG59VRQJ",
    "account_id": 1,
    "name": "JAMUL_PHU06W",
    "region": "BD"
  },
  {
    "uid": 4229562274,
    "password": "JAMIUAR_CODX-W1JFZ8GD2",
    "account_id": 1,
    "name": "JAMUL_FXAZ90",
    "region": "BD"
  },
  {
    "uid": 4229568200,
    "password": "JAMIUAR_CODX-XOLROVYPJ",
    "account_id": 1,
    "name": "JAMUL_2PC7EU",
    "region": "BD"
  },
  {
    "uid": 4229568366,
    "password": "JAMIUAR_CODX-ONN8XQKTM",
    "account_id": 1,
    "name": "JAMUL_4AU6YS",
    "region": "BD"
  },
  {
    "uid": 4229568532,
    "password": "JAMIUAR_CODX-2XPYXNBYU",
    "account_id": 1,
    "name": "JAMUL_ZYSON8",
    "region": "BD"
  },
  {
    "uid": 4229568772,
    "password": "JAMIUAR_CODX-7TJCWIPOG",
    "account_id": 1,
    "name": "JAMUL_HKYVZX",
    "region": "BD"
  },
  {
    "uid": 4229568994,
    "password": "JAMIUAR_CODX-6BZPASLWX",
    "account_id": 1,
    "name": "JAMUL_OX0WNA",
    "region": "BD"
  },
  {
    "uid": 4229570041,
    "password": "JAMIUAR_CODX-LPMZMR7LK",
    "account_id": 1,
    "name": "JAMUL_XYOCXY",
    "region": "BD"
  },
  {
    "uid": 4229570213,
    "password": "JAMIUAR_CODX-63D13UMUO",
    "account_id": 1,
    "name": "JAMUL_Q190YK",
    "region": "BD"
  },
  {
    "uid": 4229570413,
    "password": "JAMIUAR_CODX-2XJOYNGRT",
    "account_id": 1,
    "name": "JAMUL_ZPCM7R",
    "region": "BD"
  },
  {
    "uid": 4229570588,
    "password": "JAMIUAR_CODX-WTYAQDVMC",
    "account_id": 1,
    "name": "JAMUL_NNNLQ4",
    "region": "BD"
  },
  {
    "uid": 4229571194,
    "password": "JAMIUAR_CODX-2QJWYRXWI",
    "account_id": 1,
    "name": "JAMUL_K96H7H",
    "region": "BD"
  },
  {
    "uid": 4229571297,
    "password": "JAMIUAR_CODX-RZST3KHD6",
    "account_id": 1,
    "name": "JAMUL_MQWTV7",
    "region": "BD"
  },
  {
    "uid": 4229571475,
    "password": "JAMIUAR_CODX-HHPLDLZBG",
    "account_id": 1,
    "name": "JAMUL_UQMSPB",
    "region": "BD"
  },
  {
    "uid": 4229571797,
    "password": "JAMIUAR_CODX-WDMEZVBB1",
    "account_id": 1,
    "name": "JAMUL_FT7TEA",
    "region": "BD"
  },
  {
    "uid": 4229572118,
    "password": "JAMIUAR_CODX-B7PE629VA",
    "account_id": 1,
    "name": "JAMUL_D4PY2J",
    "region": "BD"
  },
  {
    "uid": 4229572398,
    "password": "JAMIUAR_CODX-GNOHBDMJV",
    "account_id": 1,
    "name": "JAMUL_AQ235K",
    "region": "BD"
  },
  {
    "uid": 4229573028,
    "password": "JAMIUAR_CODX-4WO2TLOM8",
    "account_id": 1,
    "name": "JAMUL_BT4SAP",
    "region": "BD"
  },
  {
    "uid": 4229573217,
    "password": "JAMIUAR_CODX-HMUAP1DCW",
    "account_id": 1,
    "name": "JAMUL_DFLIB9",
    "region": "BD"
  },
  {
    "uid": 4229573613,
    "password": "JAMIUAR_CODX-OGHKTOMKR",
    "account_id": 1,
    "name": "JAMUL_GS2EL6",
    "region": "BD"
  },
  {
    "uid": 4229573970,
    "password": "JAMIUAR_CODX-UCI5X1ML8",
    "account_id": 1,
    "name": "JAMUL_APQGTI",
    "region": "BD"
  },
  {
    "uid": 4229574514,
    "password": "JAMIUAR_CODX-OR2A5OOYC",
    "account_id": 1,
    "name": "JAMUL_SZN6YR",
    "region": "BD"
  },
  {
    "uid": 4229575112,
    "password": "JAMIUAR_CODX-04QBKGYHH",
    "account_id": 1,
    "name": "JAMUL_JOBPQS",
    "region": "BD"
  },
  {
    "uid": 4229576785,
    "password": "JAMIUAR_CODX-ZOENI1RRV",
    "account_id": 1,
    "name": "JAMUL_NRPDZJ",
    "region": "BD"
  },
  {
    "uid": 4229576914,
    "password": "JAMIUAR_CODX-JX41DOKL5",
    "account_id": 1,
    "name": "JAMUL_RP5ZCU",
    "region": "BD"
  },
  {
    "uid": 4229577048,
    "password": "JAMIUAR_CODX-GTWLKM9HH",
    "account_id": 1,
    "name": "JAMUL_ZUIPU1",
    "region": "BD"
  },
  {
    "uid": 4229577166,
    "password": "JAMIUAR_CODX-OV9WBFJQ1",
    "account_id": 1,
    "name": "JAMUL_LPNFDX",
    "region": "BD"
  },
  {
    "uid": 4229577327,
    "password": "JAMIUAR_CODX-AJF2N5U1M",
    "account_id": 1,
    "name": "JAMUL_1WBGSR",
    "region": "BD"
  },
  {
    "uid": 4229577923,
    "password": "JAMIUAR_CODX-FECK2M4L5",
    "account_id": 1,
    "name": "JAMUL_OMDGIU",
    "region": "BD"
  },
  {
    "uid": 4229578473,
    "password": "JAMIUAR_CODX-X4KFROJ3K",
    "account_id": 1,
    "name": "JAMUL_WLHRS3",
    "region": "BD"
  },
  {
    "uid": 4229578649,
    "password": "JAMIUAR_CODX-J1FTUG1QC",
    "account_id": 1,
    "name": "JAMUL_EZZVK8",
    "region": "BD"
  },
  {
    "uid": 4229578750,
    "password": "JAMIUAR_CODX-Z5HV1R5EB",
    "account_id": 1,
    "name": "JAMUL_LRRBHK",
    "region": "BD"
  },
  {
    "uid": 4229579047,
    "password": "JAMIUAR_CODX-HGKL9ZX21",
    "account_id": 1,
    "name": "JAMUL_4XOAKW",
    "region": "BD"
  },
  {
    "uid": 4229579500,
    "password": "JAMIUAR_CODX-HU0KCK38H",
    "account_id": 1,
    "name": "JAMUL_1C6F0A",
    "region": "BD"
  },
  {
    "uid": 4229579777,
    "password": "JAMIUAR_CODX-BSA3ALE9P",
    "account_id": 1,
    "name": "JAMUL_02JTHB",
    "region": "BD"
  },
  {
    "uid": 4229579916,
    "password": "JAMIUAR_CODX-AAHZY7N3L",
    "account_id": 1,
    "name": "JAMUL_Z8DXWP",
    "region": "BD"
  },
  {
    "uid": 4229580167,
    "password": "JAMIUAR_CODX-2MJLGLCJZ",
    "account_id": 1,
    "name": "JAMUL_F4M0XR",
    "region": "BD"
  },
  {
    "uid": 4229580313,
    "password": "JAMIUAR_CODX-DGVK1M9HZ",
    "account_id": 1,
    "name": "JAMUL_9FETU9",
    "region": "BD"
  },
  {
    "uid": 4229580409,
    "password": "JAMIUAR_CODX-GZGKYISBG",
    "account_id": 1,
    "name": "JAMUL_MPXJVH",
    "region": "BD"
  },
  {
    "uid": 4229580506,
    "password": "JAMIUAR_CODX-WLRKNWBMZ",
    "account_id": 1,
    "name": "JAMUL_JVDN6J",
    "region": "BD"
  },
  {
    "uid": 4229580590,
    "password": "JAMIUAR_CODX-93ZOVFNBK",
    "account_id": 1,
    "name": "JAMUL_LBCQHL",
    "region": "BD"
  },
  {
    "uid": 4229580682,
    "password": "JAMIUAR_CODX-YMVCBG81D",
    "account_id": 1,
    "name": "JAMUL_QI4V4K",
    "region": "BD"
  },
  {
    "uid": 4229580763,
    "password": "JAMIUAR_CODX-2AWUMRUXE",
    "account_id": 1,
    "name": "JAMUL_N85RYB",
    "region": "BD"
  },
  {
    "uid": 4229580946,
    "password": "JAMIUAR_CODX-VOKVRVECG",
    "account_id": 1,
    "name": "JAMUL_YMAOCT",
    "region": "BD"
  },
  {
    "uid": 4229581081,
    "password": "JAMIUAR_CODX-L9IGFMYEU",
    "account_id": 1,
    "name": "JAMUL_R3FCKW",
    "region": "BD"
  },
  {
    "uid": 4229581186,
    "password": "JAMIUAR_CODX-BXWVPEMW4",
    "account_id": 1,
    "name": "JAMUL_BELM6R",
    "region": "BD"
  },
  {
    "uid": 4229581324,
    "password": "JAMIUAR_CODX-ICRM3HQN3",
    "account_id": 1,
    "name": "JAMUL_2XKQGW",
    "region": "BD"
  },
  {
    "uid": 4229581568,
    "password": "JAMIUAR_CODX-4C4YUZQG7",
    "account_id": 1,
    "name": "JAMUL_BWKLPR",
    "region": "BD"
  },
  {
    "uid": 4229581685,
    "password": "JAMIUAR_CODX-7IPQYC6HZ",
    "account_id": 1,
    "name": "JAMUL_HS4ZUE",
    "region": "BD"
  },
  {
    "uid": 4229581827,
    "password": "JAMIUAR_CODX-XFP2GTS4E",
    "account_id": 1,
    "name": "JAMUL_ZLPRGV",
    "region": "BD"
  },
  {
    "uid": 4229581940,
    "password": "JAMIUAR_CODX-UUKWPKT0L",
    "account_id": 1,
    "name": "JAMUL_A1GQN6",
    "region": "BD"
  },
  {
    "uid": 4229829617,
    "password": "JAMIUAR_CODX-YXEINXWB7",
    "account_id": 1,
    "name": "JAMUL_UONHDY",
    "region": "BD"
  }
    [
  {
    "uid": 4230162189,
    "password": "JAMIUAR_CODX-1AMVG5GFA",
    "account_id": 1,
    "name": "JAMUL_0PT4NL",
    "region": "IND"
  },
  {
    "uid": 4230162336,
    "password": "JAMIUAR_CODX-PMCSY1TL3",
    "account_id": 1,
    "name": "JAMUL_EPQ3EY",
    "region": "IND"
  },
  {
    "uid": 4230162458,
    "password": "JAMIUAR_CODX-VJJWLWED5",
    "account_id": 1,
    "name": "JAMUL_XMUVE6",
    "region": "IND"
  },
  {
    "uid": 4230162622,
    "password": "JAMIUAR_CODX-TIDOE6IVE",
    "account_id": 1,
    "name": "JAMUL_MY2J4V",
    "region": "IND"
  },
  {
    "uid": 4230163361,
    "password": "JAMIUAR_CODX-45I3ANIYS",
    "account_id": 1,
    "name": "JAMUL_QHWBWD",
    "region": "IND"
  },
  {
    "uid": 4230163976,
    "password": "JAMIUAR_CODX-5YYVZMV0R",
    "account_id": 1,
    "name": "JAMUL_UN6QNE",
    "region": "IND"
  },
  {
    "uid": 4230164101,
    "password": "JAMIUAR_CODX-1GY1PQPHN",
    "account_id": 1,
    "name": "JAMUL_DTBZXT",
    "region": "IND"
  },
  {
    "uid": 4230164281,
    "password": "JAMIUAR_CODX-WGH5THPTA",
    "account_id": 1,
    "name": "JAMUL_ZBOVO8",
    "region": "IND"
  },
  {
    "uid": 4230165072,
    "password": "JAMIUAR_CODX-TN61GSGKF",
    "account_id": 1,
    "name": "JAMUL_NRTYA6",
    "region": "IND"
  },
  {
    "uid": 4230165736,
    "password": "JAMIUAR_CODX-CBJCSNKFW",
    "account_id": 1,
    "name": "JAMUL_6VZBOZ",
    "region": "IND"
  },
  {
    "uid": 4230165854,
    "password": "JAMIUAR_CODX-F3HUNS7X6",
    "account_id": 1,
    "name": "JAMUL_CCSIA0",
    "region": "IND"
  },
  {
    "uid": 4230165997,
    "password": "JAMIUAR_CODX-ZFR414V2R",
    "account_id": 1,
    "name": "JAMUL_F9A3UC",
    "region": "IND"
  },
  {
    "uid": 4230166232,
    "password": "JAMIUAR_CODX-OTFHP4JIE",
    "account_id": 1,
    "name": "JAMUL_I4PSFF",
    "region": "IND"
  },
  {
    "uid": 4230166405,
    "password": "JAMIUAR_CODX-RBZSLNRCA",
    "account_id": 1,
    "name": "JAMUL_PA69RF",
    "region": "IND"
  },
  {
    "uid": 4230166584,
    "password": "JAMIUAR_CODX-NDCFPJHCW",
    "account_id": 1,
    "name": "JAMUL_CT1UC7",
    "region": "IND"
  },
  {
    "uid": 4230166734,
    "password": "JAMIUAR_CODX-FCPUZOQEZ",
    "account_id": 1,
    "name": "JAMUL_L2QX2X",
    "region": "IND"
  },
  {
    "uid": 4230166856,
    "password": "JAMIUAR_CODX-APNB4LAHO",
    "account_id": 1,
    "name": "JAMUL_V1XRIP",
    "region": "IND"
  },
  {
    "uid": 4230167474,
    "password": "JAMIUAR_CODX-IESE4YRNV",
    "account_id": 1,
    "name": "JAMUL_ROFTZY",
    "region": "IND"
  },
  {
    "uid": 4230168256,
    "password": "JAMIUAR_CODX-2KXNKZR0H",
    "account_id": 1,
    "name": "JAMUL_8GJZQR",
    "region": "IND"
  },
  {
    "uid": 4230168392,
    "password": "JAMIUAR_CODX-IYZMLURL2",
    "account_id": 1,
    "name": "JAMUL_6JASVX",
    "region": "IND"
  },
  {
    "uid": 4230168532,
    "password": "JAMIUAR_CODX-6PSDF3HYC",
    "account_id": 1,
    "name": "JAMUL_23RNKY",
    "region": "IND"
  },
  {
    "uid": 4230168645,
    "password": "JAMIUAR_CODX-BESWOPGH5",
    "account_id": 1,
    "name": "JAMUL_GGOMEE",
    "region": "IND"
  },
  {
    "uid": 4230169279,
    "password": "JAMIUAR_CODX-CXKCAGPVF",
    "account_id": 1,
    "name": "JAMUL_ZV5LLW",
    "region": "IND"
  },
  {
    "uid": 4230169480,
    "password": "JAMIUAR_CODX-DFPL7DT8G",
    "account_id": 1,
    "name": "JAMUL_HKZAZN",
    "region": "IND"
  },
  {
    "uid": 4230169644,
    "password": "JAMIUAR_CODX-OHDORBKTY",
    "account_id": 1,
    "name": "JAMUL_ZFZJ8T",
    "region": "IND"
  },
  {
    "uid": 4230169788,
    "password": "JAMIUAR_CODX-B6TEXCXLO",
    "account_id": 1,
    "name": "JAMUL_5CHEFW",
    "region": "IND"
  },
  {
    "uid": 4230170581,
    "password": "JAMIUAR_CODX-FLDG1UKOG",
    "account_id": 1,
    "name": "JAMUL_5UQSPH",
    "region": "IND"
  },
  {
    "uid": 4230170713,
    "password": "JAMIUAR_CODX-JAMVD6H3K",
    "account_id": 1,
    "name": "JAMUL_XKVX4L",
    "region": "IND"
  },
  {
    "uid": 4230171160,
    "password": "JAMIUAR_CODX-MVMN5CKRK",
    "account_id": 1,
    "name": "JAMUL_CQQDRF",
    "region": "IND"
  },
  {
    "uid": 4230171315,
    "password": "JAMIUAR_CODX-WMTIJUFJL",
    "account_id": 1,
    "name": "JAMUL_NUMQZ4",
    "region": "IND"
  },
  {
    "uid": 4230172029,
    "password": "JAMIUAR_CODX-XE1HFNAXK",
    "account_id": 1,
    "name": "JAMUL_OWQF1K",
    "region": "IND"
  },
  {
    "uid": 4230172178,
    "password": "JAMIUAR_CODX-KMD1LDBJS",
    "account_id": 1,
    "name": "JAMUL_IAMQNL",
    "region": "IND"
  },
  {
    "uid": 4230172310,
    "password": "JAMIUAR_CODX-ECEU2V1UO",
    "account_id": 1,
    "name": "JAMUL_AGVYDM",
    "region": "IND"
  },
  {
    "uid": 4230172490,
    "password": "JAMIUAR_CODX-NWORLKWM1",
    "account_id": 1,
    "name": "JAMUL_EGM4DP",
    "region": "IND"
  },
  {
    "uid": 4230172637,
    "password": "JAMIUAR_CODX-IZ2KY4PDK",
    "account_id": 1,
    "name": "JAMUL_XUGQTD",
    "region": "IND"
  },
  {
    "uid": 4230172835,
    "password": "JAMIUAR_CODX-WJN59RZVP",
    "account_id": 1,
    "name": "JAMUL_MYA3NH",
    "region": "IND"
  },
  {
    "uid": 4230173569,
    "password": "JAMIUAR_CODX-05HH9JFS6",
    "account_id": 1,
    "name": "JAMUL_3R0A5C",
    "region": "IND"
  },
  {
    "uid": 4230173703,
    "password": "JAMIUAR_CODX-SL4HBMAIR",
    "account_id": 1,
    "name": "JAMUL_I2EHP5",
    "region": "IND"
  },
  {
    "uid": 4230174296,
    "password": "JAMIUAR_CODX-X2CJBOORO",
    "account_id": 1,
    "name": "JAMUL_QQAK2V",
    "region": "IND"
  },
  {
    "uid": 4230174512,
    "password": "JAMIUAR_CODX-KGOR1VLMA",
    "account_id": 1,
    "name": "JAMUL_IK1IKM",
    "region": "IND"
  },
  {
    "uid": 4230174658,
    "password": "JAMIUAR_CODX-VNR3HLFBA",
    "account_id": 1,
    "name": "JAMUL_U7QEVB",
    "region": "IND"
  },
  {
    "uid": 4230174797,
    "password": "JAMIUAR_CODX-BCHB1NBVG",
    "account_id": 1,
    "name": "JAMUL_5BRABQ",
    "region": "IND"
  },
  {
    "uid": 4230174941,
    "password": "JAMIUAR_CODX-5KZGM8CII",
    "account_id": 1,
    "name": "JAMUL_YYZRX7",
    "region": "IND"
  },
  {
    "uid": 4230175126,
    "password": "JAMIUAR_CODX-ZKPKRQPJP",
    "account_id": 1,
    "name": "JAMUL_SQ2OW1",
    "region": "IND"
  },
  {
    "uid": 4230175272,
    "password": "JAMIUAR_CODX-TPVYIP2QJ",
    "account_id": 1,
    "name": "JAMUL_KDK90H",
    "region": "IND"
  },
  {
    "uid": 4230175426,
    "password": "JAMIUAR_CODX-AOL1SQWRP",
    "account_id": 1,
    "name": "JAMUL_1RWA3M",
    "region": "IND"
  },
  {
    "uid": 4230175560,
    "password": "JAMIUAR_CODX-PQY8DA3K0",
    "account_id": 1,
    "name": "JAMUL_NGOQCS",
    "region": "IND"
  },
  {
    "uid": 4230176323,
    "password": "JAMIUAR_CODX-DNYG9TQXA",
    "account_id": 1,
    "name": "JAMUL_QDG3O5",
    "region": "IND"
  },
  {
    "uid": 4230176483,
    "password": "JAMIUAR_CODX-XVWPQP0J6",
    "account_id": 1,
    "name": "JAMUL_GEABR2",
    "region": "IND"
  },
  {
    "uid": 4230176662,
    "password": "JAMIUAR_CODX-VGJ8CNDE0",
    "account_id": 1,
    "name": "JAMUL_4L4MG9",
    "region": "IND"
  },
  {
    "uid": 4230177312,
    "password": "JAMIUAR_CODX-FASRNCD8S",
    "account_id": 1,
    "name": "JAMUL_JGTZXU",
    "region": "IND"
  },
  {
    "uid": 4230177422,
    "password": "JAMIUAR_CODX-V0TOPLU54",
    "account_id": 1,
    "name": "JAMUL_AQD44K",
    "region": "IND"
  }
]
]
